apilama/__init__.py
apilama/app.py
apilama/logger.py
apilama/logging_config.py
apilama/routes/__init__.py
apilama/routes/file_routes.py
apilama/routes/git_routes.py
apilama/routes/pybox_routes.py
apilama/routes/pylama_routes.py
apilama/routes/pyllm_routes.py
apilama/routes/shellama_routes.py
apilama/routes/weblama_routes.py
apilama-0.1.16.dist-info/LICENSE
apilama-0.1.16.dist-info/METADATA
apilama-0.1.16.dist-info/WHEEL
apilama-0.1.16.dist-info/RECORD
