Metadata-Version: 2.3
Name: apilama
Version: 0.1.16
Summary: Backend API service for the PyLama ecosystem
License: Apache-2.0
Author: Tom Sapletta
Author-email: info@softreck.dev
Requires-Python: >=3.8,<4.0
Classifier: License :: OSI Approved :: Apache Software License
Classifier: Programming Language :: Python :: 3
Classifier: Programming Language :: Python :: 3.8
Classifier: Programming Language :: Python :: 3.9
Classifier: Programming Language :: Python :: 3.10
Classifier: Programming Language :: Python :: 3.11
Classifier: Programming Language :: Python :: 3.12
Classifier: Programming Language :: Python :: 3.13
Project-URL: Repository, https://github.com/py-lama/apilama
